aws_recommendation_a15/__init__.py
aws_recommendation_a15/cloudwatch.py
aws_recommendation_a15/cost_estimations.py
aws_recommendation_a15/dynamodb.py
aws_recommendation_a15/ebs.py
aws_recommendation_a15/ec2.py
aws_recommendation_a15/elb.py
aws_recommendation_a15/kms.py
aws_recommendation_a15/rds.py
aws_recommendation_a15/recommendation.py
aws_recommendation_a15/redshift.py
aws_recommendation_a15/s3.py
aws_recommendation_a15/truted_advisor.py
aws_recommendation_a15/utils.py
aws_recommendation_a15-0.1.0.dist-info/LICENCE
aws_recommendation_a15-0.1.0.dist-info/METADATA
aws_recommendation_a15-0.1.0.dist-info/WHEEL
aws_recommendation_a15-0.1.0.dist-info/top_level.txt
aws_recommendation_a15-0.1.0.dist-info/RECORD
